mmconf/__init__.py
mmconf/config.py
mmconf/lazy.py
mmconf/fileio/__init__.py
mmconf/fileio/io.py
mmconf/fileio/handlers/__init__.py
mmconf/fileio/handlers/base.py
mmconf/fileio/handlers/json_handler.py
mmconf/fileio/handlers/registry_utils.py
mmconf/fileio/handlers/toml_handler.py
mmconf/fileio/handlers/yaml_handler.py
mmconf/utils/__init__.py
mmconf/utils/misc.py
mmconf/utils/package_utils.py
mmconf/utils/path.py
mmconf/utils/version_utils.py
mmconf-0.1.3.dist-info/METADATA
mmconf-0.1.3.dist-info/WHEEL
mmconf-0.1.3.dist-info/RECORD
