Metadata-Version: 2.4
Name: mmconf
Version: 0.1.3
Summary: A Python package for managing configuration files in a structured way.
Requires-Python: >=3.11
Requires-Dist: addict>=2.4.0
Requires-Dist: numpy>=1.26.4
Requires-Dist: packaging>=20.0
Requires-Dist: pyyaml>=6.0.2
Requires-Dist: regex>=2024.11.6
Requires-Dist: rich>=14.0.0
Requires-Dist: rtoml>=0.12.0
Requires-Dist: yapf>=0.43.0
